main.py
passforgesafedev-1.0.0.dist-info/licenses/LICENSE
passforgesafedev-1.0.0.dist-info/METADATA
passforgesafedev-1.0.0.dist-info/WHEEL
passforgesafedev-1.0.0.dist-info/top_level.txt
passforgesafedev-1.0.0.dist-info/RECORD
